interface_meta/__init__.py
interface_meta/_version.py
interface_meta/decorators.py
interface_meta/interface.py
interface_meta/utils/__init__.py
interface_meta/utils/conformance.py
interface_meta/utils/docs.py
interface_meta/utils/errors.py
interface_meta/utils/inspection.py
interface_meta/utils/reporting.py
interface_meta-1.2.5.dist-info/LICENSE
interface_meta-1.2.5.dist-info/METADATA
interface_meta-1.2.5.dist-info/WHEEL
interface_meta-1.2.5.dist-info/top_level.txt
interface_meta-1.2.5.dist-info/RECORD
